{"aux-power":{"hp":"60","make":"Pathfinder","type":"Diesel"},"bal-disp":"57.14%","ballast":"12000 lbs. /  5443 kgs.","beam":"13.33' /  4.06m","builder":"Snug Harbor Boat Works","construct":"FG","designer":"Scott Kaufman","designers":{"designed-by":{"link":"view_designer.asp?designer_id=147","text":"Scott Kaufman"}},"disp":"21000 lbs./  9526 kgs.","disp-len":"185.08","draft-max":"8.25' /  2.51m","first-built":"1981","hull-type":"Fin w/spade rudder","id":"10","imgs":[],"listed-sa":"993 ft2 /  92.25 m2","loa":"46.00' /  14.02m","lwl":"37.00' /  11.28m","name":"KAUFMAN 46","rig-type":"Masthead Sloop","sa-disp":"20.95","tanks":{"fuel":"40 gals. /  151 ltrs.","water":"115 gals. /  435 ltrs."},"update":{"deleted":0,"errors":0,"inserted":0,"replaced":1,"skipped":0,"unchanged":0}}