{"aux-power":{"hp":"36","make":"Bukh","model":"DV36SME","type":"Diesel"},"beam":"10.00' /  3.05m","builder":"LM Glasfiber A/S (DEN)","builders":{"built-by":{"link":"view_builder.asp?builder_id=379","text":"LM Glasfiber"}},"built":"311","construct":"FG","designer":"Bent Juul Andersen","designers":{"designed-by":{"link":"view_designer.asp?designer_id=465","text":"Bent Juul Andersen"}},"disp":"11000 lbs./  4990 kgs.","disp-len":"271.49","draft-max":"4.90' /  1.49m","first-built":"1977","hull-type":"Long Keel","id":"1071","imgs":[{"link":"imagehelper.asp?file_id=1442","text":"LM 30 photo on sailboatdata.com"}],"last-built":"1990","listed-sa":"361 ft2 /  33.54 m2","loa":"31.83' /  9.70m","lwl":"26.25' /  8.00m","name":"LM 30","notes":"Single or Bilge keels. Later built by Scanyachts. \r\n","rig-dimensions":{"dl-ratio":"271.49","e":"10.20' /  3.11m","est-forestay-len":"38.61' /  11.77m","i":"37.10' /  11.31m","j":"10.70' /  3.26m","p":"31.80' /  9.69m","sa-disp":"11.71","safore":"198.49 ft2 /  18.44 m2","samain":"162.18 ft2 /  15.07 m2","totalcalcsa":"360.67 ft2 /  33.51 m2"},"rig-type":"Masthead Sloop","sa-disp":"11.72","update":{"deleted":0,"errors":0,"inserted":0,"replaced":1,"skipped":0,"unchanged":0}}