{"bal-disp":"35.14%","ballast":"2425 lbs. /  1100 kgs.","beam":"10.25' /  3.12m","builder":"Tanzer Industries Ltd. (CAN)","builders":{"built-by":{"link":"view_builder.asp?builder_id=56","text":"Tanzer Industries Ltd."}},"construct":"FG","designer":"Joubert/Nivelt","designers":{"designed-by":{"link":"view_designer.asp?designer_id=119","text":"Joubert-Nivelt"}},"disp":"6900 lbs./  3130 kgs.","disp-len":"216.01","draft-max":"5.25' /  1.60m","first-built":"1986","hull-type":"Fin w/spade rudder","id":"1206","imgs":[{"link":"imagehelper.asp?file_id=8024","text":"Tanzer 29 photo on sailboatdata.com"},{"link":"imagehelper.asp?file_id=5078","text":"Tanzer 29 drawing on sailboatdata.com"}],"listed-sa":"391 ft2 /  36.32 m2","loa":"29.00' /  8.84m","lwl":"24.25' /  7.39m","name":"TANZER 29","notes":"Shoal draft: 4.0'","rig-dimensions":{"dl-ratio":"216.01","e":"10.17' /  3.10m","est-forestay-len":"40.09' /  12.22m","i":"38.45' /  11.72m","j":"11.35' /  3.46m","p":"33.62' /  10.25m","sa-disp":"17.23","safore":"218.20 ft2 /  20.27 m2","samain":"170.96 ft2 /  15.88 m2","totalcalcsa":"389.16 ft2 /  36.15 m2"},"rig-type":"Masthead Sloop","sa-disp":"17.31","update":{"deleted":0,"errors":0,"inserted":0,"replaced":1,"skipped":0,"unchanged":0}}