{"bal-disp":"38.68%","ballast":"850 lbs. /  386 kgs.","beam":"8.00' /  2.44m","builder":"AMF (USA)","builders":[{"built-by":{"link":"view_builder.asp?builder_id=105","text":"Alcort (USA)"}}],"construct":"FG","designer":"Ted Hood","designers":{"designed-by":{"link":"view_designer.asp?designer_id=26","text":"Ted Hood"}},"disp":"2200 lbs./  998 kgs.","disp-len":"180.77","draft-max":"4.00' /  1.22m","draft-min":"1.00' /  0.30m","first-built":"1977","hull-type":"Lifting Keel","id":"122","imgs":[{"link":"imagehelper.asp?file_id=2940","text":"AMF 2100 photo on sailboatdata.com"},{"link":"imagehelper.asp?file_id=4198","text":"AMF 2100 drawing on sailboatdata.com"}],"listed-sa":"209 ft2 /  19.42 m2","loa":"21.08' /  6.43m","lwl":"17.58' /  5.36m","name":"AMF 2100","rig-dimensions":{"dl-ratio":"180.77","e":"9.00' /  2.74m","est-forestay-len":"25.21' /  7.68m","i":"23.91' /  7.29m","j":"8.00' /  2.44m","p":"25.25' /  7.70m","sa-disp":"19.84","safore":"95.64 ft2 /  8.88 m2","samain":"113.63 ft2 /  10.56 m2","totalcalcsa":"209.27 ft2 /  19.44 m2"},"rig-type":"Fractional  Sloop","sa-disp":"19.82","update":{"deleted":0,"errors":0,"inserted":0,"replaced":1,"skipped":0,"unchanged":0}}