{"bal-disp":"40.90%","ballast":"4500 lbs. /  2041 kgs.","beam":"11.60' /  3.54m","builder":"Island Packet Yachts (USA)","builders":{"built-by":{"link":"view_builder.asp?builder_id=128","text":"Island Packet Yachts"}},"built":"262","construct":"FG","designer":"Bob Johnson","designers":{"designed-by":{"link":"view_designer.asp?designer_id=160","text":"Robert K. Johnson"}},"disp":"11000 lbs./  4990 kgs.","disp-len":"229.80","draft-max":"4.00' /  1.22m","first-built":"1983","hull-type":"Long Keel","id":"1324","imgs":[{"link":"imagehelper.asp?file_id=8913","text":"Island Packet 31 photo on sailboatdata.com"},{"link":"imagehelper.asp?file_id=8914","text":"Island Packet 31 drawing on sailboatdata.com"}],"last-built":"1989","listed-sa":"530 ft2 /  49.24 m2","loa":"31.00' /  9.45m","lwl":"27.75' /  8.46m","name":"ISLAND PACKET 31","notes":"Keel/CB also available.\r\nDraft - BU: 3.0'/BD: 7.0'","related-links":{"island-packet-yacht-owners":{"link":"http://www.iphomeport.com","text":"www.iphomeport.com"}},"rig-dimensions":{"dl-ratio":"229.80","e":"14.00' /  4.27m","est-forestay-len":"42.18' /  12.86m","i":"39.50' /  12.04m","j":"14.80' /  4.51m","p":"34.00' /  10.36m","sa-disp":"17.21","safore":"292.30 ft2 /  27.15 m2","samain":"238.00 ft2 /  22.11 m2","totalcalcsa":"530.30 ft2 /  49.26 m2"},"rig-type":"Cutter","sa-disp":"17.20","tanks":{"fuel":"25 gals. /  95 ltrs.","water":"70 gals. /  265 ltrs."},"update":{"deleted":0,"errors":0,"inserted":0,"replaced":1,"skipped":0,"unchanged":0}}