{"bal-disp":"37.09%","bal-type":"Iron","ballast":"500 lbs. /  227 kgs.","beam":"6.33' /  1.93m","builder":"Henry McCune/Wesco Marine/Coronado Yachts","builders":[{"built-by":{"link":"view_builder.asp?builder_id=18","text":"Coronado Yachts"}}],"built":"690","construct":"FG","designer":"Ted Carpentier","designers":{"designed-by":{"link":"view_designer.asp?designer_id=225","text":"Ted Carpentier"}},"disp":"1350 lbs./  612 kgs.","disp-len":"178.57","draft-max":"3.00' /  0.91m","first-built":"1959","hull-type":"Fin w/spade rudder","id":"140","imgs":[{"link":"imagehelper.asp?file_id=6336","text":"Victory 21 photo on sailboatdata.com"},{"link":"imagehelper.asp?file_id=5376","text":"Victory 21 drawing on sailboatdata.com"}],"last-built":"1980","listed-sa":"190 ft2 /  17.65 m2","loa":"21.00' /  6.40m","lwl":"15.00' /  4.57m","name":"VICTORY 21","notes":"The VICTORY 21 was first manufactured by Henry R. McCune (later the builder of the YORKTOWN sailboats)  as a one-design class boat. \r\nSome 126 boats were built before the operation was sold to Wesco Marine in 1964. \r\nAnother model called the AURORA 21 had the same hull but with a larger cabin.\r\nChanges to the original design made by Wesco included making the cockpit self-bailing and installing a sliding hatch on the cabin. The cabin entrance was redesigned so it could be secured with a lock (hull#490-500)\r\nBetween 1969 and 1970, the boats were built by Coronado Yachts.  Later, production was resumed by Catalina Yachts  where it became the CAPRI VICTORY. \r\n","related-links":{"victory-21-site":{"link":"http://www.victory21.org","text":"www.victory21.org"}},"rig-dimensions":{"dl-ratio":"178.57","e":"9.70' /  2.96m","est-forestay-len":"25.47' /  7.76m","i":"24.40' /  7.44m","j":"7.30' /  2.23m","p":"20.75' /  6.32m","sa-disp":"24.90","safore":"89.06 ft2 /  8.27 m2","samain":"100.64 ft2 /  9.35 m2","totalcalcsa":"189.70 ft2 /  17.62 m2"},"rig-type":"Masthead Sloop","sa-disp":"24.94","see-also":{"related-boat":{"link":"viewrecord.asp?class_id=3874","text":"AURORA  21"}},"update":{"deleted":0,"errors":0,"inserted":0,"replaced":1,"skipped":0,"unchanged":0}}