{"bal-disp":"40.94%","ballast":"4300 lbs. /  1950 kgs.","beam":"10.00' /  3.05m","builder":"Coronado Yachts (USA)","builders":{"built-by":{"link":"view_builder.asp?builder_id=18","text":"Coronado Yachts"}},"construct":"FG","designer":"William Tripp Jr.","designers":{"designed-by":{"link":"view_designer.asp?designer_id=13","text":"William H. Tripp Jr."}},"disp":"10500 lbs./  4763 kgs.","disp-len":"209.69","draft-max":"5.00' /  1.52m","first-built":"1966","hull-type":"Fin w/spade rudder","id":"1492","imgs":[{"link":"imagehelper.asp?file_id=4603","text":"Coronado 34 drawing on sailboatdata.com"}],"last-built":"1974","listed-sa":"544 ft2 /  50.54 m2","loa":"34.65' /  10.56m","lwl":"28.17' /  8.59m","name":"CORONADO 34","rig-dimensions":{"dl-ratio":"209.69","e":"15.00' /  4.57m","est-forestay-len":"43.30' /  13.20m","i":"41.25' /  12.57m","j":"13.16' /  4.01m","p":"33.25' /  10.13m","sa-disp":"17.44","safore":"271.43 ft2 /  25.22 m2","samain":"249.38 ft2 /  23.17 m2","totalcalcsa":"520.80 ft2 /  48.38 m2"},"rig-type":"Masthead Sloop","sa-disp":"18.21","update":{"deleted":0,"errors":0,"inserted":0,"replaced":1,"skipped":0,"unchanged":0}}