{"aux-power":{"type":"Diesel"},"bal-disp":"29.65%","ballast":"4300 lbs. /  1950 kgs.","beam":"10.83' /  3.30m","builder":"Easterly Yachts (USA)","builders":{"built-by":{"link":"view_builder.asp?builder_id=495","text":"Easterly Yachts (USA)"}},"construct":"FG","designer":"Brennan","disp":"14500 lbs./  6577 kgs.","disp-len":"311.26","draft-max":"5.30' /  1.62m","first-built":"1976","hull-type":"Fin Keel","id":"1846","imgs":[],"listed-sa":"594 ft2 /  55.18 m2","loa":"36.00' /  10.97m","lwl":"27.50' /  8.38m","name":"EASTERLY 36","rig-dimensions":{"dl-ratio":"311.26","e":"13.50' /  4.11m","est-forestay-len":"47.06' /  14.34m","i":"44.50' /  13.56m","j":"15.30' /  4.66m","p":"37.50' /  11.43m","sa-disp":"16.03","safore":"340.43 ft2 /  31.63 m2","samain":"253.13 ft2 /  23.52 m2","totalcalcsa":"593.55 ft2 /  55.14 m2"},"rig-type":"Masthead Sloop","sa-disp":"16.04","tanks":{"fuel":"40 gals. /  151 ltrs.","water":"92 gals. /  348 ltrs."},"update":{"deleted":0,"errors":0,"inserted":0,"replaced":1,"skipped":0,"unchanged":0}}