{"aux-power":{"type":"Diesel"},"bal-disp":"41.38%","ballast":"7000 lbs. /  3175 kgs.","beam":"11.50' /  3.51m","builder":"Pearson Yachts (USA)","builders":{"built-by":{"link":"view_builder.asp?builder_id=14","text":"Pearson Yachts"}},"construct":"FG","designer":"William Shaw","designers":{"designed-by":{"link":"view_designer.asp?designer_id=72","text":"William Shaw"}},"disp":"16915 lbs./  7673 kgs.","disp-len":"279.68","draft-max":"5.50' /  1.68m","first-built":"1984","hull-type":"Fin with rudder on skeg","id":"2090","imgs":[{"link":"imagehelper.asp?file_id=5736","text":"Pearson 386 photo on sailboatdata.com"},{"link":"imagehelper.asp?file_id=10277","text":"Pearson 386 drawing on sailboatdata.com"}],"last-built":"1985","listed-sa":"684 ft2 /  63.54 m2","loa":"38.25' /  11.66m","lwl":"30.00' /  9.14m","name":"PEARSON 386","notes":"The PEARSON 386 is the aft cockpit version of the PEARSON 385.","rig-dimensions":{"dl-ratio":"279.68","e":"14.50' /  4.42m","est-forestay-len":"50.10' /  15.27m","i":"47.30' /  14.42m","j":"16.50' /  5.03m","p":"40.50' /  12.34m","sa-disp":"16.67","safore":"390.23 ft2 /  36.25 m2","samain":"293.63 ft2 /  27.28 m2","totalcalcsa":"683.85 ft2 /  63.53 m2"},"rig-type":"Cutter","sa-disp":"16.67","tanks":{"fuel":"45 gals. /  170 ltrs.","water":"150 gals. /  568 ltrs."},"updated":"2014-09-01T04:11:11.267Z"}