{"aux-power":{"hp":"90","make":"Ford Lehman","type":"Diesel"},"bal-disp":"37.50%","ballast":"12000 lbs. /  5443 kgs.","beam":"12.83' /  3.91m","builder":"Vagabond/Blue Water Yacht Builders (TAIWAN)","builders":{"built-by":{"link":"view_builder.asp?builder_id=623","text":"Blue Water Yacht Builders Ltd. (TAIWAN)"}},"construct":"FG","designer":"George H. Stadel III","designers":{"designed-by":{"link":"view_designer.asp?designer_id=146","text":"George Stadel III"}},"disp":"32000 lbs./  14515 kgs.","disp-len":"363.47","draft-max":"5.50' /  1.68m","first-built":"1978","hull-type":"Fin with rudder on skeg","id":"2152","imgs":[{"link":"imagehelper.asp?file_id=1022","text":"Vagabond 42 photo on sailboatdata.com"},{"link":"imagehelper.asp?file_id=3500","text":"Vagabond 42 drawing on sailboatdata.com"}],"last-built":"1990","listed-sa":"869 ft2 /  80.73 m2","loa":"42.00' /  12.80m","lwl":"34.00' /  10.36m","name":"VAGABOND 42","notes":"Also called WESTWIND 42.","rig-dimensions":{"dl-ratio":"363.47","e":"14.25' /  4.34m","est-forestay-len":"51.81' /  15.79m","ey":"8.37' /  2.55m","i":"48.00' /  14.63m","j":"19.50' /  5.94m","p":"42.00' /  12.80m","py":"24.30' /  7.41m","sa-disp":"13.85","safore":"468.00 ft2 /  43.48 m2","samain":"299.25 ft2 /  27.80 m2","totalcalcsa":"868.95 ft2 /  80.73 m2"},"rig-type":"Staysail Ketch","sa-disp":"13.85","tanks":{"fuel":"110 gals. /  416 ltrs.","water":"140 gals. /  530 ltrs."},"update":{"deleted":0,"errors":0,"inserted":0,"replaced":1,"skipped":0,"unchanged":0}}