{"aux-power":{"hp":"85","make":"Perkins","type":"Diesel"},"bal-disp":"34.14%","ballast":"14000 lbs. /  6350 kgs.","beam":"15.00' /  4.57m","builder":"Morgan Yacht Corp. (USA)","builders":{"built-by":{"link":"view_builder.asp?builder_id=81","text":"Morgan Yachts"}},"construct":"FG","designer":"Jack Cory/Charles Morgan","designers":{"designed-by":{"link":"view_designer.asp?designer_id=49","text":"Charles Morgan"}},"disp":"41000 lbs./  18598 kgs.","disp-len":"238.43","draft-max":"10.33' /  3.15m","draft-min":"5.16' /  1.57m","first-built":"1974","hull-type":"Keel/Cbrd.","id":"2738","imgs":[{"link":"imagehelper.asp?file_id=9672","text":"Morgan 51 OI photo on sailboatdata.com"},{"link":"imagehelper.asp?file_id=6301","text":"Morgan Out Island 51 drawing on sailboatdata.com"}],"last-built":"1981","listed-sa":"1122 ft2 /  104.23 m2","loa":"51.50' /  15.70m","logo":"imagehelper_insig.asp?file_id=162","lwl":"42.50' /  12.95m","name":"MORGAN OUT ISLAND 51","notes":"Later (1980) became the MORGAN OUT ISLAND 512.","rig-dimensions":{"mast-height-from-dwl":"62.00' /  18.90m"},"rig-type":"Staysail Ketch","sa-disp":"15.16","tanks":{"fuel":"300 gals. /  1136 ltrs.","water":"265 gals. /  1003 ltrs."},"update":{"deleted":0,"errors":0,"inserted":0,"replaced":1,"skipped":0,"unchanged":0}}