{"aux-power":{"hp":"37","make":"Perkins","model":"4.108 M","type":"Diesel"},"bal-disp":"44.91%","bal-type":"Lead","ballast":"11900 lbs. /  5398 kgs.","beam":"13.41' /  4.09m","builder":"Nautor","builders":{"built-by":{"link":"view_builder.asp?builder_id=104","text":"Nautor (Swan sailboats)"}},"built":"32","construct":"FG","designer":"Sparkman & Stephens","designers":{"designed-by":{"link":"view_designer.asp?designer_id=12","text":"Sparkman & Stephens"}},"disp":"26500 lbs./  12020 kgs.","disp-len":"319.52","draft-max":"7.30' /  2.23m","first-built":"1976","hull-type":"Fin with rudder on skeg","id":"2772","imgs":[{"link":"imagehelper.asp?file_id=1385","text":"Swan 431 drawing on sailboatdata.com"}],"last-built":"1978","listed-sa":"896 ft2 /  83.24 m2","loa":"43.25' /  13.18m","lwl":"33.33' /  10.16m","name":"SWAN 431","notes":"S&S #2238-C1.","rig-dimensions":{"dl-ratio":"319.52","e":"13.75' /  4.19m","est-forestay-len":"61.67' /  18.80m","i":"59.00' /  17.98m","j":"17.95' /  5.47m","p":"53.25' /  16.23m","sa-disp":"16.19","safore":"529.53 ft2 /  49.19 m2","samain":"366.09 ft2 /  34.01 m2","totalcalcsa":"895.62 ft2 /  83.20 m2"},"rig-type":"Masthead Sloop","sa-disp":"16.19","updated":"2014-09-01T04:08:08.004Z"}