{"beam":"14.00' /  4.27m","builder":"Dennis Choate","builders":{"built-by":{"link":"view_builder.asp?builder_id=127","text":"Dencho Marine"}},"construct":"FG","designer":"Scott Kaufman","designers":{"designed-by":{"link":"view_designer.asp?designer_id=147","text":"Scott Kaufman"}},"disp":"22983 lbs./  10425 kgs.","disp-len":"198.51","draft-max":"8.50' /  2.59m","first-built":"1981","hull-type":"Fin w/spade rudder","id":"2835","imgs":[],"listed-sa":"1050 ft2 /  97.54 m2","loa":"48.00' /  14.63m","lwl":"37.25' /  11.35m","name":"CHOATE 48","rig-dimensions":{"dl-ratio":"198.51","e":"15.30' /  4.66m","est-forestay-len":"65.95' /  20.10m","i":"63.00' /  19.20m","j":"19.50' /  5.94m","p":"57.00' /  17.37m","sa-disp":"20.87","safore":"614.25 ft2 /  57.06 m2","samain":"436.05 ft2 /  40.51 m2","totalcalcsa":"1,050.30 ft2 /  97.57 m2"},"rig-type":"Masthead Sloop","sa-disp":"20.86","update":{"deleted":0,"errors":0,"inserted":0,"replaced":1,"skipped":0,"unchanged":0}}