{"beam":"17.08' /  5.21m","builder":"Camper & Nicholson","builders":{"built-by":{"link":"view_builder.asp?builder_id=96","text":"Camper & Nicholson"}},"construct":"FG","designer":"Camper & Nicholson","disp":"111700 lbs./  50667 kgs.","disp-len":"308.05","draft-max":"8.50' /  2.59m","first-built":"1975","hull-type":"Fin Keel","id":"2879","imgs":[{"link":"imagehelper.asp?file_id=280","text":"Nicholson 70 photo on sailboatdata.com"}],"listed-sa":"2000 ft2 /  185.8 m2","loa":"70.00' /  21.34m","lwl":"54.50' /  16.61m","name":"NICHOLSON 70","rig-dimensions":{"dl-ratio":"308.05","e":"22.00' /  6.71m","est-forestay-len":"80.39' /  24.50m","ey":"12.25' /  3.73m","i":"76.10' /  23.20m","j":"25.90' /  7.89m","p":"68.80' /  20.97m","py":"42.08' /  12.83m","sa-disp":"13.87","safore":"985.50 ft2 /  91.55 m2","samain":"756.80 ft2 /  70.31 m2","totalcalcsa":"2,000.04 ft2 /  185.80 m2"},"rig-type":"Masthead  Ketch","sa-disp":"13.87","update":{"deleted":0,"errors":0,"inserted":0,"replaced":1,"skipped":0,"unchanged":0}}