{"bal-disp":"44.10%","bal-type":"Iron","ballast":"1500 lbs. /  680 kgs.","beam":"7.58' /  2.31m","builder":"Sonic Sailboats Ltd. (CAN)","construct":"FG","designer":"Joseph D'Alessio","disp":"3400 lbs./  1542 kgs.","disp-len":"189.73","draft-max":"3.75' /  1.14m","first-built":"1981","hull-type":"Fin w/transom hung rudder","id":"290","imgs":[{"link":"imagehelper.asp?file_id=3033","text":"Sonic 23 photo on sailboatdata.com"},{"link":"imagehelper.asp?file_id=675","text":"Sonic 23 drawing on sailboatdata.com"}],"listed-sa":"242 ft2 /  22.48 m2","loa":"23.00' /  7.01m","lwl":"20.00' /  6.10m","name":"SONIC 23","rig-dimensions":{"mast-height-from-dwl":"30.67' /  9.35m"},"rig-type":"Masthead Sloop","sa-disp":"17.17","update":{"deleted":0,"errors":0,"inserted":0,"replaced":1,"skipped":0,"unchanged":0}}