{"beam":"11.00' /  3.35m","builder":"Camper & Nicholson","builders":{"built-by":{"link":"view_builder.asp?builder_id=96","text":"Camper & Nicholson"}},"built":"25","construct":"FG","designer":"Ron Holland","designers":{"designed-by":{"link":"view_designer.asp?designer_id=37","text":"Ron Holland"}},"disp":"11500 lbs./  5216 kgs.","disp-len":"199.98","draft-max":"6.07' /  1.85m","first-built":"1979","hull-type":"Fin w/spade rudder","id":"3049","imgs":[{"link":"imagehelper.asp?file_id=3224","text":"nicholson 345 drawing on sailboatdata.com"}],"listed-sa":"656 ft2 /  60.94 m2","loa":"34.50' /  10.52m","lwl":"29.50' /  8.99m","name":"NICHOLSON 345","notes":"Built in Brazil as the FAST 345.(1984)","rig-dimensions":{"dl-ratio":"199.98","e":"14.00' /  4.27m","est-forestay-len":"38.28' /  11.67m","i":"36.00' /  10.97m","j":"13.00' /  3.96m","p":"42.25' /  12.88m","sa-disp":"16.69","safore":"234.00 ft2 /  21.74 m2","samain":"295.75 ft2 /  27.48 m2","totalcalcsa":"529.75 ft2 /  49.21 m2"},"rig-type":"Fractional  Sloop","sa-disp":"20.67","update":{"deleted":0,"errors":0,"inserted":0,"replaced":1,"skipped":0,"unchanged":0}}