{"aux-power":{"hp":"40","make":"Yanmar","model":"3JH3","type":"Diesel"},"bal-disp":"36.05%","bal-type":"Lead","ballast":"7119 lbs. /  3229 kgs.","beam":"12.50' /  3.81m","builder":"David Sadler (UK)","builders":[{"built-by":{"link":"view_builder.asp?builder_id=68","text":"Sadler Yachts"}}],"built":"34","construct":"FG","designer":"Stephen Jones","designers":{"designed-by":{"link":"view_designer.asp?designer_id=137","text":"Stephen Jones"}},"disp":"19749 lbs./  8958 kgs.","disp-len":"275.46","draft-max":"5.33' /  1.62m","first-built":"1990","hull-type":"Wing Keel","id":"3316","imgs":[{"link":"imagehelper.asp?file_id=1130","text":"Starlight 39 photo on sailboatdata.com"}],"last-built":"1994","listed-sa":"713 ft2 /  66.24 m2","loa":"38.83' /  11.84m","lwl":"31.75' /  9.68m","name":"STARLIGHT 39","notes":"Dimensions shown here are for MII version.\r\nAlso called SADLER 38.\r\nDeep draft fin: 2.09m/6.83'.","rig-dimensions":{"mast-height-from-dwl":"56.83' /  17.32m"},"rig-type":"Masthead Sloop","sa-disp":"15.67","tanks":{"fuel":"40 gals. /  151 ltrs.","water":"50 gals. /  189 ltrs."},"update":{"deleted":0,"errors":0,"inserted":0,"replaced":1,"skipped":0,"unchanged":0}}