{"bal-disp":"40.03%","bal-type":"Lead","ballast":"1300 lbs. /  590 kgs.","beam":"8.00' /  2.44m","builder":"S2 Yachts","builders":{"built-by":{"link":"view_builder.asp?builder_id=143","text":"S2 Yachts (USA)"}},"built":"404","construct":"FG","designer":"Graham & Schlageter","designers":{"designed-by":{"link":"view_designer.asp?designer_id=94","text":"Graham & Schlageter"}},"disp":"3250 lbs./  1474 kgs.","disp-len":"229.15","draft-max":"4.00' /  1.22m","first-built":"1978","hull-type":"Fin w/spade rudder","id":"405","imgs":[{"link":"imagehelper.asp?file_id=7858","text":"S2 7.3 photo on sailboatdata.com"},{"link":"imagehelper.asp?file_id=6205","text":"S2 7.3 drawing on sailboatdata.com"}],"last-built":"1987","listed-sa":"255 ft2 /  23.69 m2","loa":"23.83' /  7.26m","lwl":"18.50' /  5.64m","name":"S2 7.3","notes":"Shoal draft: 2.83'/.86m\r\n","rig-dimensions":{"mast-height-from-dwl":"31.67' /  9.65m"},"rig-type":"Masthead Sloop","sa-disp":"18.64","tanks":{"water":"15 gals. /  57 ltrs."},"updated":"2014-09-01T04:16:14.727Z"}