{"aux-power":{"type":"Gas"},"bal-disp":"37.50%","ballast":"3000 lbs. /  1361 kgs.","beam":"8.07' /  2.46m","builder":"Seafair","construct":"Wood","designer":"Ben Seaborn","designers":{"designed-by":{"link":"view_designer.asp?designer_id=48","text":"Ben Seaborn"}},"disp":"8000 lbs./  3629 kgs.","disp-len":"155.59","draft-max":"5.42' /  1.65m","first-built":"1960","hull-type":"Fin Keel","id":"4319","imgs":[{"link":"imagehelper.asp?file_id=10307","text":"Seafair 32 photo on sailboatdata.com"}],"loa":"32.00' /  9.75m","lwl":"28.42' /  8.66m","name":"SEAFAIR 32","notes":"Thanks to Elizabeth Becker for providing photo.","rig-type":"Masthead Sloop","tanks":{"fuel":"30 gals. /  114 ltrs.","water":"50 gals. /  189 ltrs."},"update":{"deleted":0,"errors":0,"inserted":0,"replaced":1,"skipped":0,"unchanged":0}}