{"aux-power":{"type":"Diesel"},"bal-disp":"33.21%","ballast":"3925 lbs. /  1780 kgs.","beam":"12.00' /  3.66m","builder":"Bavaria Yachts (GER)","builders":{"built-by":{"link":"view_builder.asp?builder_id=116","text":"Bavaria Yachts (GER)"}},"construct":"FG","designer":"J & J Design","designers":{"designed-by":{"link":"view_designer.asp?designer_id=100","text":"J&J Design"}},"disp":"11817 lbs./  5360 kgs.","disp-len":"209.09","draft-max":"6.00' /  1.83m","first-built":"2000","hull-type":"Fin w/spade rudder","id":"4841","imgs":[{"link":"imagehelper.asp?file_id=9383","text":"Bavaria 37 photo on sailboatdata.com"}],"listed-sa":"599 ft2 /  55.65 m2","loa":"37.83' /  11.53m","lwl":"29.33' /  8.94m","name":"BAVARIA 37","notes":"Similar to BAVARIA 36 (1998).","rig-dimensions":{"dl-ratio":"209.09","e":"14.60' /  4.45m","est-forestay-len":"42.91' /  13.08m","i":"40.70' /  12.41m","j":"13.60' /  4.15m","p":"44.10' /  13.44m","sa-disp":"18.53","safore":"276.76 ft2 /  25.71 m2","samain":"321.93 ft2 /  29.91 m2","totalcalcsa":"598.69 ft2 /  55.62 m2"},"rig-type":"Masthead Sloop","sa-disp":"18.54","tanks":{"fuel":"46 gals. /  174 ltrs.","water":"46 gals. /  174 ltrs."},"update":{"deleted":0,"errors":0,"inserted":0,"replaced":1,"skipped":0,"unchanged":0}}