{"aux-power":{"type":"Diesel"},"bal-disp":"50.00%","bal-type":"Iron","ballast":"1700 lbs. /  771 kgs.","beam":"7.25' /  2.21m","builder":"Robert Ives Boatbuilders Ltd. (UK)","builders":{"built-by":{"link":"view_builder.asp?builder_id=235","text":"Deacons Boat Yard Ltd."}},"construct":"FG","designer":"Ian Haney","designers":{"designed-by":{"link":"view_designer.asp?designer_id=316","text":"Ian Haney"}},"disp":"3400 lbs./  1542 kgs.","disp-len":"260.26","draft-max":"3.25' /  0.99m","first-built":"1967","hull-type":"Fin w/spade rudder","id":"4991","imgs":[{"link":"imagehelper.asp?file_id=6886","text":"Galion 22 photo on sailboatdata.com"},{"link":"imagehelper.asp?file_id=6885","text":"Galion 22 drawing on sailboatdata.com"}],"listed-sa":"199 ft2 /  18.49 m2","loa":"22.00' /  6.71m","lwl":"18.00' /  5.49m","name":"GALION 22","notes":"In 1968 a GALION 22 won both the Round the Island Race and the JOG Single-handed Race skippered by her designer, Ian Haney.","related-links":{"galion-22-owners-association":{"link":"http://www.galion22.co.uk","text":"www.galion22.co.uk"}},"rig-dimensions":{"dl-ratio":"260.26","e":"9.00' /  2.74m","est-forestay-len":"23.88' /  7.28m","i":"22.25' /  6.78m","j":"8.67' /  2.64m","p":"22.86' /  6.97m","sa-disp":"14.14","safore":"96.45 ft2 /  8.96 m2","samain":"102.87 ft2 /  9.56 m2","totalcalcsa":"199.32 ft2 /  18.52 m2"},"rig-type":"Fractional  Sloop","sa-disp":"14.12","tanks":{"fuel":"5 gals. /  19 ltrs.","water":"4 gals. /  15 ltrs."},"update":{"deleted":0,"errors":0,"inserted":0,"replaced":1,"skipped":0,"unchanged":0}}