{"aux-power":{"hp":"29","make":"Volvo","type":"Diesel"},"bal-disp":"33.62%","ballast":"4299 lbs. /  1950 kgs.","beam":"12.14' /  3.70m","builder":"Comar","builders":{"built-by":{"link":"view_builder.asp?builder_id=43","text":"Comar Yachts"}},"built":"122","construct":"FG","designer":"Groupe Finot","designers":{"designed-by":{"link":"view_designer.asp?designer_id=41","text":"Jean Marie Finot (Groupe Finot)"}},"disp":"12786 lbs./  5800 kgs.","disp-len":"161.61","draft-max":"6.56' /  2.00m","first-built":"1987","hull-type":"Fin w/spade rudder","id":"5173","imgs":[{"link":"imagehelper.asp?file_id=4388","text":"Comet 375 photo on sailboatdata.com"},{"link":"imagehelper.asp?file_id=4643","text":"Comet 375 drawing on sailboatdata.com"}],"last-built":"1993","loa":"37.73' /  11.50m","lwl":"32.81' /  10.00m","name":"COMET 375","rig-type":"Masthead Sloop","update":{"deleted":0,"errors":0,"inserted":0,"replaced":1,"skipped":0,"unchanged":0}}