{"bal-disp":"35.00%","ballast":"1543 lbs. /  700 kgs.","beam":"6.77' /  2.06m","builder":"Comar (ITA)","builders":{"built-by":{"link":"view_builder.asp?builder_id=43","text":"Comar Yachts"}},"built":"245","construct":"FG","designer":"Groupe Finot","designers":{"designed-by":{"link":"view_designer.asp?designer_id=41","text":"Jean Marie Finot (Groupe Finot)"}},"disp":"4409 lbs./  2000 kgs.","disp-len":"193.96","draft-max":"4.76' /  1.45m","first-built":"1978","hull-type":"Fin w/spade rudder","id":"5179","imgs":[{"link":"imagehelper.asp?file_id=4379","text":"Comet 800 photo on sailboatdata.com"}],"last-built":"1986","listed-sa":"364 ft2 /  33.82 m2","loa":"25.59' /  7.80m","lwl":"21.65' /  6.60m","name":"COMET 800","rig-type":"Masthead Sloop","sa-disp":"21.72","tanks":{"fuel":"7 gals. /  26 ltrs.","water":"16 gals. /  61 ltrs."},"update":{"deleted":0,"errors":0,"inserted":0,"replaced":1,"skipped":0,"unchanged":0}}