{"aux-power":{"url":{"link":"http://www.rogersyachtdesign.com","text":"www.rogersyachtdesign.com"}},"bal-type":"Lead","beam":"10.99' /  3.35m","builder":"2GM","built":"7","construct":"FG","designer":"Rogers Yachts Design","disp":"5732 lbs./  2600 kgs.","disp-len":"82.97","draft-max":"6.40' /  1.95m","first-built":"1993","hull-type":"Fin Keel w/bulb","id":"5307","imgs":[],"listed-sa":"710 ft2 /  65.96 m2","loa":"31.36' /  9.56m","lwl":"31.36' /  9.56m","name":"ROGERS 30","notes":"Designed to the Whitbread/Mount Gay 30 Rule, which never quite caught on.","rig-type":"Fractional  Sloop","sa-disp":"35.57","update":{"deleted":0,"errors":0,"inserted":0,"replaced":1,"skipped":0,"unchanged":0}}