{"bal-disp":"38.92%","bal-type":"Lead","ballast":"650 lbs. /  295 kgs.","beam":"8.10' /  2.47m","builder":"Bravura Yachts Inc. (USA)","builders":{"built-by":{"link":"view_builder.asp?builder_id=576","text":"Bravura Yachts Inc."}},"built":"11","construct":"FG","designer":"Alan Andrews","designers":{"designed-by":{"link":"view_designer.asp?designer_id=77","text":"Alan Andrews"}},"disp":"1670 lbs./  758 kgs.","disp-len":"119.68","draft-max":"5.00' /  1.52m","first-built":"2002","hull-type":"Fin w/bulb & spade rudder","id":"5373","imgs":[{"link":"imagehelper.asp?file_id=7457","text":"Governor's Cup 21 photo on sailboatdata.com"},{"link":"imagehelper.asp?file_id=7456","text":"Governors Cup 21 on sailboatdata.com"}],"listed-sa":"231 ft2 /  21.46 m2","loa":"21.00' /  6.40m","lwl":"18.40' /  5.61m","name":"GOVERNOR'S CUP 21 (GC-21)","notes":"The GOVERNOR'S CUP 21 (or GC-21) was commissioned and the first 11 were built at the behest of the Newport Balboa Sailing and Seamanship Association (NBSSA)as a match racer for the Governor's Cup Match Racing Series, first held in California in 1967.","rig-dimensions":{"dl-ratio":"119.68","e":"10.00' /  3.05m","est-forestay-len":"26.97' /  8.22m","i":"25.80' /  7.86m","isp":"29' /  8.84m","j":"7.85' /  2.39m","p":"26.00' /  7.92m","sa-disp":"26.34","safore":"101.27 ft2 /  9.41 m2","samain":"130.00 ft2 /  12.08 m2","spl":"8.6' /  2.62m","totalcalcsa":"231.27 ft2 /  21.48 m2"},"rig-type":"Fractional  Sloop","sa-disp":"26.31","update":{"deleted":0,"errors":0,"inserted":0,"replaced":1,"skipped":0,"unchanged":0}}