{"bal-disp":"35.83%","ballast":"1433 lbs. /  650 kgs.","beam":"9.67' /  2.95m","builder":"Cantieri Barberis (ITA)","builders":{"built-by":{"link":"view_builder.asp?builder_id=171","text":"Barberis (Cantieri)"}},"construct":"FG","designer":"Delio Barberis/Lanfranco Soma","disp":"4000 lbs./  1814 kgs.","disp-len":"167.70","draft-max":"5.50' /  1.68m","first-built":"1978","hull-type":"Fin w/spade rudder","id":"561","imgs":[{"link":"imagehelper.asp?file_id=3603","text":"Show 27 photo on sailboatdata.com"},{"link":"imagehelper.asp?file_id=6086","text":"Show 27 drawing on sailboatdata.com"}],"listed-sa":"298 ft2 /  27.68 m2","loa":"27.50' /  8.38m","lwl":"22.00' /  6.71m","name":"SHOW 27","rig-dimensions":{"dl-ratio":"167.70","e":"9.35' /  2.85m","est-forestay-len":"32.71' /  9.97m","i":"31.04' /  9.46m","j":"10.33' /  3.15m","p":"27.16' /  8.28m","sa-disp":"18.29","safore":"160.32 ft2 /  14.89 m2","samain":"126.97 ft2 /  11.80 m2","totalcalcsa":"287.29 ft2 /  26.69 m2"},"rig-type":"Masthead Sloop","sa-disp":"18.97","update":{"deleted":0,"errors":0,"inserted":0,"replaced":1,"skipped":0,"unchanged":0}}