{"beam":"5.50' /  1.68m","builder":"Ian Ridge (UK)","built":"1000","construct":"Plywood","designer":"Peter Milne","designers":{"designed-by":{"link":"view_designer.asp?designer_id=131","text":"Peter Milne"}},"disp":"187 lbs./  85 kgs.","draft-max":"3.58' /  1.09m","draft-min":"0.58' /  0.18m","first-built":"1970","hull-type":"Centerboard Dinghy","id":"5819","imgs":[],"listed-sa":"150 ft2 /  13.93 m2","loa":"14.50' /  4.42m","name":"MARAUDER (MILNE)","notes":"Called the MIRROR 14 when first introduced in 1970 after a sponsorship from the 'Daily Mirror' newspaper.  \r\nIt is a trapeze dinghy originally designed for plywood 'stitch & glue' construction. \r\nSpin. SA 150 sq ft.","rig-type":"Fractional  Sloop","sa-disp":"73.44","update":{"deleted":0,"errors":0,"inserted":0,"replaced":1,"skipped":0,"unchanged":0}}