{"beam":"7.50' /  2.29m","construct":"Wood/FG","designer":"Graham Johnston","disp":"147 lbs./  67 kgs.","disp-len":"11.58","draft-max":"3.00' /  0.91m","draft-min":"0.50' /  0.15m","first-built":"1966","hull-type":"Catamaran Twin Dbrd.","id":"6005","imgs":[{"link":"imagehelper.asp?file_id=6644","text":"Australis Catamaran drawing on sailboatdata.com"}],"listed-sa":"150 ft2 /  13.93 m2","loa":"18.00' /  5.49m","lwl":"17.83' /  5.43m","name":"AUSTRALIS CATAMARAN","notes":"Australian designed 'A' class that trounced the competition at the 1967 IYRU selection trails for a new single handed catamaran. Almost immediately it was granted international status and licenses were granted to a number of builders around the world. However, the class never achieved any wide spread popularity and the International designation was withdrawn in 1973.","rig-type":"Cat (rotating spar)","sa-disp":"86.21","see-also":{"related-boat":{"link":"viewrecord.asp?class_id=4294","text":"A CLASS CATAMARAN"}},"update":{"deleted":0,"errors":0,"inserted":0,"replaced":1,"skipped":0,"unchanged":0}}