{"aux-power":{"hp":"12","make":"Yanmar","type":"Diesel"},"bal-disp":"47.96%","bal-type":"Lead","ballast":"3500 lbs. /  1588 kgs.","beam":"11.33' /  3.45m","builder":"Irwin Yacht & Marine Corporation (USA)","builders":{"built-by":{"link":"view_builder.asp?builder_id=82","text":"Irwin Yachts"}},"construct":"FG","designer":"Ted Irwin","designers":{"designed-by":{"link":"view_designer.asp?designer_id=50","text":"Ted Irwin"}},"disp":"7300 lbs./  3311 kgs.","disp-len":"223.79","draft-max":"6.50' /  1.98m","draft-min":"3.50' /  1.07m","first-built":"1977","hull-type":"Lifting Keel","id":"6037","imgs":[],"listed-sa":"412 ft2 /  38.27 m2","loa":"32.00' /  9.75m","lwl":"24.42' /  7.44m","name":"IRWIN 1/2 TON MKII","notes":"According to Irwin documentation, as compared to the first version, the MKII has a transom hung rudder, drop/dagger keel, (draft is the same) softer chine and broader beam aft.","rig-type":"Masthead Sloop","sa-disp":"17.57","see-also":{"related-boat":{"link":"viewrecord.asp?class_id=1262","text":"IRWIN 1/2 TON"}},"tanks":{"fuel":"14 gals. /  53 ltrs.","water":"28 gals. /  106 ltrs."},"update":{"deleted":0,"errors":0,"inserted":0,"replaced":1,"skipped":0,"unchanged":0}}