{"bal-disp":"22.29%","ballast":"245 lbs. /  111 kgs.","beam":"6.76' /  2.06m","builder":"Florence Marine Int. (UK)","construct":"FG","designer":"John Bennet","designers":{"designed-by":{"link":"view_designer.asp?designer_id=241","text":"John A. Bennett"}},"disp":"1098 lbs./  498 kgs.","disp-len":"160.79","draft-max":"1.48' /  0.45m","first-built":"1975","hull-type":"Twin Keel","id":"6078","imgs":[{"link":"imagehelper.asp?file_id=6872","text":"Pedro 17 drawing on sailboatdata.com"}],"listed-sa":"99 ft2 /  9.2 m2","loa":"17.22' /  5.25m","lwl":"14.50' /  4.42m","name":"PEDRO 17","notes":"A variant of the SEAHAWK 17 with more freeboard, bilge keels, and smaller rig. \r\nAccording to the brochure, available in various stages of construction. An inboard engine and wheel steering was available. A fixed keel version,  called the SENORITA, was sold by this same company.","related-links":{"seahawk-17-uk":{"link":"http://www.seahawk17.org.uk","text":"www.seahawk17.org.uk"}},"rig-type":"Masthead Sloop","sa-disp":"14.91","see-also":{"related-boat":{"link":"viewrecord.asp?class_id=6065","text":"SEAHAWK 17"}},"update":{"deleted":0,"errors":0,"inserted":0,"replaced":1,"skipped":0,"unchanged":0}}