{"beam":"12.99' /  3.96m","builders":{"built-by":{"link":"view_builder.asp?builder_id=408","text":"Fyne Boat Kits (UK)"}},"construct":"Plywood","designer":"Ian Proctor","designers":{"designed-by":{"link":"view_designer.asp?designer_id=105","text":"Ian Proctor"}},"disp":"160 lbs./  73 kgs.","disp-len":"46.97","draft-max":"3.33' /  1.01m","draft-min":"0.42' /  0.13m","first-built":"1961","hull-type":"Centerboard Dinghy","id":"6110","imgs":[{"link":"imagehelper.asp?file_id=6939","text":"SigneT Dinghy photo on sailboatdata.com"}],"listed-sa":"88 ft2 /  8.18 m2","loa":"12.00' /  3.66m","lwl":"11.50' /  3.51m","name":"SIGNET DINGHY (PROCTOR)","notes":"Designed for the home builder. Specifications originally set by the Sunday Times of London.","related-links":{"signet-class-owners-association":{"link":"http://www.sailsignet.org.uk","text":"www.sailsignet.org.uk"}},"rig-type":"Fractional  Sloop","sa-disp":"47.80","update":{"deleted":0,"errors":0,"inserted":0,"replaced":1,"skipped":0,"unchanged":0}}