{"aux-power":{"hp":"47","make":"Perkins","model":"4.108","type":"Diesel"},"bal-disp":"50.61%","ballast":"10990 lbs. /  4985 kgs.","beam":"12.70' /  3.87m","builder":"Moody & Son Ltd. (UK)","builders":{"built-by":{"link":"view_builder.asp?builder_id=97","text":"Moody Yachts (A. H. Moody & Sons)"}},"built":"3","construct":"FG","designer":"Laurent Giles & Partners","designers":{"designed-by":{"link":"view_designer.asp?designer_id=123","text":"Jack Laurent Giles"}},"disp":"21715 lbs./  9850 kgs.","disp-len":"397.48","draft-max":"6.00' /  1.83m","first-built":"1980","hull-type":"Fin (shoal draft)","id":"6610","imgs":[{"link":"imagehelper.asp?file_id=8206","text":"Moody Grenadier 119 drawing on sailboatdata.com"}],"last-built":"1983","listed-sa":"7920 ft2 /  735.77 m2","loa":"39.17' /  11.94m","lwl":"29.00' /  8.84m","name":"MOODY GRENADIER 119","rig-type":"Masthead  Ketch","sa-disp":"163.44","tanks":{"fuel":"120 gals. /  454 ltrs.","water":"90 gals. /  341 ltrs."},"update":{"deleted":0,"errors":0,"inserted":0,"replaced":1,"skipped":0,"unchanged":0}}