{"bal-disp":"52.38%","bal-type":"Lead","ballast":"2425 lbs. /  1100 kgs.","beam":"8.20' /  2.50m","builder":"Lion Yacht","construct":"FG","designer":"John Corby","designers":{"designed-by":{"link":"view_designer.asp?designer_id=389","text":"John Corby"}},"disp":"4630 lbs./  2100 kgs.","disp-len":"170.55","draft-max":"6.10' /  1.86m","first-built":"2003","hull-type":"Fin w/bulb & spade rudder","id":"6635","imgs":[{"link":"imagehelper.asp?file_id=9971","text":"Corby 25 photo on sailboatdata.com"}],"listed-sa":"451 ft2 /  41.9 m2","loa":"25.00' /  7.62m","lwl":"22.97' /  7.00m","name":"CORBY 25","notes":"Also called AXION 25.","rig-type":"Fractional  Sloop","sa-disp":"26.05","update":{"deleted":0,"errors":0,"inserted":0,"replaced":1,"skipped":0,"unchanged":0}}