{"aux-power":{"hp":"18","make":"Yanmar","model":"2GM20","type":"Diesel"},"bal-disp":"31.25%","bal-type":"Lead/Water","ballast":"2205 lbs. /  1000 kgs.","beam":"11.55' /  3.52m","builder":"Bellamer (FIN)","builders":{"built-by":{"link":"view_builder.asp?builder_id=253","text":"Aerodyne Yachts Ltd."}},"construct":"Composite","designer":"Groupe Finot","designers":{"designed-by":{"link":"view_designer.asp?designer_id=41","text":"Jean Marie Finot (Groupe Finot)"}},"disp":"7055 lbs./  3200 kgs.","disp-len":"76.70","draft-max":"8.20' /  2.50m","first-built":"2000","hull-type":"Fin w/bulb & twin rudders","id":"6686","imgs":[{"link":"imagehelper.asp?file_id=8385","text":"Aerodyne 35 photo on sailboatdata.com"},{"link":"imagehelper.asp?file_id=8384","text":"Aerodyne 35 drawing on sailboatdata.com"}],"listed-sa":"754 ft2 /  70.05 m2","loa":"35.50' /  10.82m","lwl":"34.50' /  10.52m","name":"AERODYNE 35","notes":"Also called SOUTH 35. \r\nWater ballast:1763 lbs./800 kgs.\r\nA number of different rigs available.","rig-dimensions":{"dl-ratio":"76.70","e":"16.50' /  5.03m","est-forestay-len":"42.67' /  13.00m","i":"40.70' /  12.41m","isp":"57.25' /  17.45m","j":"12.80' /  3.90m","p":"50.52' /  15.40m","sa-disp":"29.55","safore":"260.48 ft2 /  24.20 m2","samain":"416.79 ft2 /  38.72 m2","spl":"18.21' /  5.55m","totalcalcsa":"677.27 ft2 /  62.92 m2"},"rig-type":"Frac. Sloop (Rotating Spar)","sa-disp":"32.90","tanks":{"fuel":"21 gals. /  79 ltrs.","water":"39 gals. /  148 ltrs."},"update":{"deleted":0,"errors":0,"inserted":0,"replaced":1,"skipped":0,"unchanged":0}}