{"bal-disp":"56.80%","bal-type":"Lead","ballast":"7513 lbs. /  3408 kgs.","beam":"11.22' /  3.42m","builder":"Cavalier Yachts (NZ)","builders":{"built-by":{"link":"view_builder.asp?builder_id=289","text":"Cavalier Yachts"}},"built":"35","construct":"FG","designer":"Bob Salthouse","disp":"13228 lbs./  6000 kgs.","disp-len":"230.26","draft-max":"5.97' /  1.82m","first-built":"1973","hull-type":"Fin with rudder on skeg","id":"6692","imgs":[{"link":"imagehelper.asp?file_id=10895","text":"Cavalier 39 drawing on sailboatdata.com"}],"last-built":"1979","listed-sa":"742 ft2 /  68.93 m2","loa":"38.98' /  11.88m","lwl":"29.49' /  8.99m","name":"CAVALIER 39","notes":"Thanks to 'kestrahl' for providing information on this yacht.\r\nApparently there were a number of  versions and details vary.","rig-type":"Masthead Sloop","sa-disp":"21.30","tanks":{"fuel":"32 gals. /  121 ltrs.","water":"132 gals. /  500 ltrs."},"updated":"2014-08-31T23:45:22.420Z"}