{"bal-disp":"50.65%","ballast":"7800 lbs. /  3538 kgs.","beam":"9.67' /  2.95m","builder":"Benello (ITA)","built":"19","construct":"FG","designer":"Sparkman & Stephens","designers":{"designed-by":{"link":"view_designer.asp?designer_id=12","text":"Sparkman & Stephens"}},"disp":"15400 lbs./  6985 kgs.","disp-len":"414.62","draft-max":"6.00' /  1.83m","first-built":"1965","hull-type":"Fin with rudder on skeg","id":"6705","imgs":[],"listed-sa":"540 ft2 /  50.17 m2","loa":"36.00' /  10.97m","lwl":"25.50' /  7.77m","name":"GAIA 36","notes":"Based on 'Hestia', a  successful racer under the RORC rule.(S&S#1478)\r\nThis was the first production version of this design. \r\nThere were a number of other later variants including the SWAN 36, and the SIGMA 36 by Cheoy Lee.","rig-type":"Masthead Sloop","sa-disp":"14.01","see-also":{"related-boat":{"link":"viewrecord.asp?class_id=1735","text":"SWAN 36"}},"update":{"deleted":0,"errors":0,"inserted":0,"replaced":1,"skipped":0,"unchanged":0}}