{"aux-power":{"type":"Diesel"},"bal-disp":"37.50%","ballast":"8400 lbs. /  3810 kgs.","beam":"13.42' /  4.09m","builder":"Gulfstar Yachts (USA)","builders":{"built-by":{"link":"view_builder.asp?builder_id=205","text":"Gulfstar Yachts"}},"built":"42","construct":"FG","disp":"22400 lbs./  10161 kgs.","disp-len":"250.65","draft-max":"5.42' /  1.65m","first-built":"1986","hull-type":"Fin w/spade rudder","id":"6963","imgs":[],"loa":"42.33' /  12.90m","lwl":"34.17' /  10.42m","name":"GULFSTAR 42 (CSY 42 PH)","notes":"See CSY 42 PH.","rig-dimensions":{"dl-ratio":"250.65","e":"16.10' /  4.91m","est-forestay-len":"45.93' /  14.00m","i":"42.00' /  12.80m","j":"18.60' /  5.67m","p":"43.00' /  13.11m","sa-disp":"14.89","safore":"390.60 ft2 /  36.29 m2","samain":"346.15 ft2 /  32.16 m2","totalcalcsa":"736.75 ft2 /  68.44 m2"},"rig-type":"Masthead Sloop","see-also":{"related-boat":{"link":"viewrecord.asp?class_id=1611","text":"CSY 42 PH"}},"update":{"deleted":0,"errors":0,"inserted":0,"replaced":1,"skipped":0,"unchanged":0}}