{"aux-power":{"hp":"36","make":"Bukh","type":"Diesel"},"beam":"12.43' /  3.79m","builder":"Oyster Marine (UK)","builders":{"built-by":{"link":"view_builder.asp?builder_id=238","text":"Oyster Marine"}},"built":"18","construct":"FG","designer":"Holman & Pye","designers":{"designed-by":{"link":"view_designer.asp?designer_id=282","text":"Holman & Pye"}},"disp":"16094 lbs./  7300 kgs.","disp-len":"288.58","draft-max":"5.25' /  1.60m","first-built":"1979","hull-type":"Fin with rudder on skeg","id":"7045","imgs":[],"last-built":"1982","loa":"35.76' /  10.90m","lwl":"29.20' /  8.90m","name":"OYSTER MARINER 35","notes":"Center cockpit Sloop or ketch.","rig-type":"Masthead  Ketch","tanks":{"fuel":"60 gals. /  227 ltrs.","water":"120 gals. /  454 ltrs."},"update":{"deleted":0,"errors":0,"inserted":0,"replaced":1,"skipped":0,"unchanged":0}}