{"bal-disp":"40.00%","ballast":"441 lbs. /  200 kgs.","beam":"6.17' /  1.88m","builder":"Lynaes Shipyard (SWE)","construct":"Wood/FG","designer":"Ole Jensen/Christian Madsen","disp":"1102 lbs./  500 kgs.","disp-len":"148.72","draft-max":"1.64' /  0.50m","first-built":"1820","hull-type":"Fin w/transom hung rudder","id":"7085","imgs":[{"link":"imagehelper.asp?file_id=9191","text":"Lynaes 14 photo on sailboatdata.com"},{"link":"imagehelper.asp?file_id=11094","text":"Lynaes 14 drawing on sailboatdata.com"}],"listed-sa":"123 ft2 /  11.43 m2","loa":"15.26' /  4.65m","lwl":"14.90' /  4.54m","name":"LYNAES 14","notes":"From a type designed and built by Ole Jensen in 1820. The first fiberglass version was built in around 1960.(It is thought that several hundred of these were built.) Later, some were built in Australia, and another version was built in Canada called the NORDICA 16.","related-links":{"lynaes-14-home-page":{"link":"http://lynaes14.dk","text":"lynaes14.dk"}},"rig-type":"Fractional  Sloop","sa-disp":"18.48","update":{"deleted":0,"errors":0,"inserted":0,"replaced":1,"skipped":0,"unchanged":0}}