{"aux-power":{"hp":"75","make":"Yanmar","model":"4JH2-HTBE","type":"Diesel"},"bal-disp":"28.75%","bal-type":"Lead","ballast":"11500 lbs. /  5216 kgs.","beam":"15.00' /  4.57m","builder":"Ta Shing Yacht Building (TAIWAN)","builders":{"built-by":{"link":"view_builder.asp?builder_id=11","text":"Ta Shing Yacht Building Ltd."}},"construct":"FG","designer":"Bill Dixon","designers":{"designed-by":{"link":"view_designer.asp?designer_id=156","text":"Bill Dixon"}},"disp":"40000 lbs./  18144 kgs.","disp-len":"242.41","draft-max":"6.75' /  2.06m","first-built":"1999","hull-type":"Fin with rudder on skeg","id":"7204","imgs":[],"last-built":"2002","listed-sa":"1100 ft2 /  102.19 m2","loa":"50.08' /  15.26m","lwl":"41.92' /  12.78m","name":"TASWELL 50","notes":"Extended version of the TASWELL 49 (1989)\r\nDRAFT (SHOAL KEEL):\t6.08'/1.98m \r\nDRAFT (SCHEEL KEEL):\t5.5'/1.68m","rig-type":"Cutter","sa-disp":"15.11","tanks":{"fuel":"113 gals. /  428 ltrs.","water":"141 gals. /  534 ltrs."},"update":{"deleted":0,"errors":0,"inserted":0,"replaced":1,"skipped":0,"unchanged":0}}