{"aux-power":{"type":"Diesel"},"bal-disp":"32.68%","ballast":"3351 lbs. /  1520 kgs.","beam":"10.75' /  3.28m","builder":"Jeanneau","builders":{"built-by":{"link":"view_builder.asp?builder_id=48","text":"Jeanneau (FRA)"}},"construct":"FG","designer":"Jacques Fauroux","disp":"10253 lbs./  4651 kgs.","disp-len":"178.29","draft-max":"6.00' /  1.83m","first-built":"1998","hull-type":"Fin w/bulb & spade rudder","id":"7289","imgs":[],"listed-sa":"473 ft2 /  43.94 m2","loa":"33.75' /  10.29m","lwl":"29.50' /  8.99m","name":"STARDUST 342/343","notes":"Similar to SUN ODYSSEY 34.2 aka JEANNEAU 34.2. and widely seen in the European/Med/Agean charter trade.","rig-dimensions":{"dl-ratio":"178.29","e":"13.78' /  4.20m","est-forestay-len":"43.09' /  13.13m","i":"41.66' /  12.70m","j":"11.00' /  3.35m","p":"35.43' /  10.80m","sa-disp":"16.10","safore":"229.13 ft2 /  21.29 m2","samain":"244.11 ft2 /  22.68 m2","totalcalcsa":"473.24 ft2 /  43.96 m2"},"rig-type":"Masthead Sloop","sa-disp":"16.09","see-also":{"related-boat":{"link":"viewrecord.asp?class_id=5217","text":"SUN ODYSSEY 34.2 (JEANNEAU)"}},"tanks":{"fuel":"28 gals. /  106 ltrs.","water":"37 gals. /  140 ltrs."},"update":{"deleted":0,"errors":0,"inserted":0,"replaced":1,"skipped":0,"unchanged":0}}