{"bal-disp":"333.33%","bal-type":"Gravel","ballast":"838 lbs. /  380 kgs.","beam":"6.56' /  2.00m","builder":"A.J.S. Marine Service (UK)","construct":"FG/Wood","designer":"Laurent Giles","designers":{"designed-by":{"link":"view_designer.asp?designer_id=123","text":"Jack Laurent Giles"}},"disp":"251 lbs./  114 kgs.","draft-max":"2.50' /  0.76m","draft-min":"1.25' /  0.38m","first-built":"1989","hull-type":"Centerboard (Trunk)","id":"7375","imgs":[{"link":"imagehelper.asp?file_id=9638","text":"Jolly Boat (Laurent Giles) photo on sailboatdata.com"}],"listed-sa":"150 ft2 /  13.93 m2","loa":"15.09' /  4.60m","name":"JOLLY BOAT (LAURENT  GILES)","notes":"Traditional open cockpit day boat. Based on an earlier version designed for plywood construction.\r\nLength w/bowsprit: 20'/6.1m.\r\nKetch (balanced lug) or gaff head sloop.\r\nBallast consists of sacks filled with gravel.","rig-type":"Gaff head  Ketch","sa-disp":"60.37","update":{"deleted":0,"errors":0,"inserted":0,"replaced":1,"skipped":0,"unchanged":0}}