{"beam":"5.74' /  1.75m","construct":"FG","designer":"Ian Howlett & John Craig","designers":{"designed-by":{"link":"view_designer.asp?designer_id=300","text":"Ian Howlett"}},"disp":"220 lbs./  100 kgs.","first-built":"1990","hull-type":"Dbrd. Dinghy","id":"7387","imgs":[],"listed-sa":"152 ft2 /  14.12 m2","loa":"15.55' /  4.74m","name":"ISO DINGHY","notes":"Beam with detachable wings 2.15m/7.05'.\r\nSpinnaker area 18.80sq m","rig-dimensions":{"i":"7.05' /  2.15m"},"rig-type":"Fractional  Sloop","sa-disp":"66.79","update":{"deleted":0,"errors":0,"inserted":0,"replaced":1,"skipped":0,"unchanged":0}}