{"aux-power":{"hp":"107","make":"Volvo Penta","model":"D3-110","type":"Diesel"},"bal-disp":"33.49%","ballast":"13955 lbs. /  6330 kgs.","beam":"15.06' /  4.59m","builder":"Najad Yachts (SWE)","builders":{"built-by":{"link":"view_builder.asp?builder_id=215","text":"Najad Yachts (SWE)"}},"construct":"FG","designer":"Judel/Vrolijk","designers":{"designed-by":{"link":"view_designer.asp?designer_id=18","text":"Judel/Vrolijk & Co."}},"disp":"41667 lbs./  18900 kgs.","disp-len":"188.76","draft-max":"14.60' /  4.45m","first-built":"2007","hull-type":"Fin w/bulb & spade rudder","id":"7507","imgs":[{"link":"imagehelper.asp?file_id=9897","text":"Najad 505 photo on sailboatdata.com"},{"link":"imagehelper.asp?file_id=10375","text":"Najad 505 drawing on sailboatdata.com"}],"listed-sa":"1420 ft2 /  131.92 m2","loa":"50.20' /  15.30m","lwl":"46.19' /  14.08m","name":"NAJAD 505","notes":"Shallow draft: 2.1m/6.89'","rig-type":"Fractional  Sloop","sa-disp":"18.99","tanks":{"mast-height-from-dwl":"74.50' /  22.71m"},"update":{"deleted":0,"errors":0,"inserted":0,"replaced":1,"skipped":0,"unchanged":0}}