{"beam":"6.25' /  1.91m","builder":"Sovereign 96 Inc.(USA)","builders":{"built-by":{"link":"view_builder.asp?builder_id=186","text":"Sovereign Yachts (Custom Fiberglass Products)"}},"construct":"FG","designer":"Reuben Trane","designers":{"designed-by":{"link":"view_designer.asp?designer_id=398","text":"Reuben Trane"}},"disp":"900 lbs./  408 kgs.","disp-len":"66.10","draft-max":"3.50' /  1.07m","draft-min":"0.75' /  0.23m","first-built":"1984","hull-type":"Centerboard (Trunk)","id":"7598","imgs":[{"link":"imagehelper.asp?file_id=10074","text":"Bay Hen 21 photo on sailboatdata.com"}],"listed-sa":"175 ft2 /  16.26 m2","loa":"21.00' /  6.40m","lwl":"18.25' /  5.56m","name":"BAY HEN 21","notes":"Twin, centerboards, (side by side in separate trunks).","rig-type":"Gaff head Cat","sa-disp":"30.09","update":{"deleted":0,"errors":0,"inserted":0,"replaced":1,"skipped":0,"unchanged":0}}