{"bal-disp":"67.37%","bal-type":"Lead","ballast":"5644 lbs. /  2560 kgs.","beam":"7.55' /  2.30m","builder":"Maxi Yachts","builders":{"built-by":{"link":"view_builder.asp?builder_id=438","text":"Maxi Yachts (SWE)"}},"construct":"FG","designer":"PELLE PETTERSSON","designers":{"designed-by":{"link":"view_designer.asp?designer_id=132","text":"Pelle Petterson"}},"disp":"8377 lbs./  3800 kgs.","disp-len":"119.65","draft-max":"6.89' /  2.10m","first-built":"2004","hull-type":"Fin w/bulb & spade rudder","id":"7713","imgs":[{"link":"imagehelper.asp?file_id=10327","text":"SM40 photo on sailboatdata.com"},{"link":"imagehelper.asp?file_id=10326","text":"SM40 drawing on sailboatdata.com"}],"listed-sa":"645 ft2 /  59.92 m2","loa":"39.37' /  12.00m","lwl":"31.50' /  9.60m","name":"SM40","notes":"SWEDISH MATCH 40.\r\nClosely resembling a mini ACC boat, the SM40 was designed specifically for the World Match Racing Tour.\r\nFits within a standard 40ft shipping container.\r\nSA GENOA: 32 sqm\r\nSA SPIN.: 85 sqm","related-links":{"world-match-racing-tour":{"link":"http://www.wmrt.com","text":"www.wmrt.com"}},"rig-type":"Fractional  Sloop","sa-disp":"25.10","update":{"deleted":0,"errors":0,"inserted":0,"replaced":1,"skipped":0,"unchanged":0}}