{"bal-disp":"30.02%","ballast":"2100 lbs. /  953 kgs.","beam":"11.18' /  3.41m","builder":"J Boats Tillotson Pearson (USA)","builders":{"built-by":{"link":"view_builder.asp?builder_id=54","text":"J Boats"}},"built":"554","construct":"FG","designer":"Johnstone","designers":{"designed-by":{"link":"view_designer.asp?designer_id=15","text":"Rod Johnstone"}},"disp":"7000 lbs./  3175 kgs.","disp-len":"200.00","draft-max":"5.25' /  1.60m","first-built":"1979","hull-type":"Fin w/transom hung rudder","id":"796","imgs":[{"link":"imagehelper.asp?file_id=775","text":"J-30 photo on sailboatdata.com"},{"link":"imagehelper.asp?file_id=8138","text":"J/30 drawing on sailboatdata.com"}],"last-built":"1986","listed-sa":"444 ft2 /  41.25 m2","loa":"29.83' /  9.09m","lwl":"25.00' /  7.62m","name":"J/30","related-links":{"j-30-class-association":{"link":"http://www.j30.org","text":"www.j30.org"}},"rig-dimensions":{"dl-ratio":"200.00","e":"13.00' /  3.96m","est-forestay-len":"36.07' /  10.99m","i":"34.19' /  10.42m","j":"11.50' /  3.51m","p":"38.00' /  11.58m","sa-disp":"19.46","safore":"196.59 ft2 /  18.26 m2","samain":"247.00 ft2 /  22.95 m2","totalcalcsa":"443.59 ft2 /  41.21 m2"},"rig-type":"Fractional  Sloop","sa-disp":"19.47","update":{"deleted":0,"errors":0,"inserted":0,"replaced":1,"skipped":0,"unchanged":0}}