{"aux-power":{"hp":"30","make":"Universal","model":"Atomic 4","type":"Gas"},"bal-disp":"30.42%","ballast":"3650 lbs. /  1656 kgs.","beam":"10.00' /  3.05m","builder":"Cheoy Lee Shipyard Ltd.(HK)","builders":{"built-by":{"link":"view_builder.asp?builder_id=95","text":"Cheoy Lee Shipyard"}},"construct":"FG","designer":"A. E. Luders","designers":{"designed-by":{"link":"view_designer.asp?designer_id=9","text":"Alfred E. Luders"}},"disp":"12000 lbs./  5443 kgs.","disp-len":"387.52","draft-max":"4.00' /  1.22m","first-built":"1975","hull-type":"Long Keel","id":"825","imgs":[{"link":"imagehelper.asp?file_id=5311","text":"Clipper 33 (Cheoy Lee) photo on sailboatdata.com"},{"link":"imagehelper.asp?file_id=1857","text":"Cheoy Lee Clipper 33 drawing on sailboatdata.com"}],"listed-sa":"472 ft2 /  43.85 m2","loa":"32.92' /  10.03m","lwl":"24.00' /  7.32m","name":"CLIPPER 33 (CHEOY LEE)","notes":"Engine was Atomic-4 30 HP with optional Perkins 4/108 or Volvo Penta MD-11C type 25 HP available.\r\nCutter or ketch.","related-links":{"cheoy-lee-association-web-site":{"link":"http://www.cheoyleeassociation.com","text":"www.cheoyleeassociation.com"}},"rig-dimensions":{"dl-ratio":"387.52","e":"12.50' /  3.81m","est-forestay-len":"38.24' /  11.66m","ey":"9.00' /  2.74m","i":"34.50' /  10.52m","j":"16.50' /  5.03m","p":"30.00' /  9.14m","py":"21.00' /  6.40m","sa-disp":"17.36","safore":"284.63 ft2 /  26.44 m2","samain":"187.50 ft2 /  17.42 m2","totalcalcsa":"566.63 ft2 /  52.64 m2"},"rig-type":"Staysail Ketch","sa-disp":"14.46","update":{"deleted":0,"errors":0,"inserted":0,"replaced":1,"skipped":0,"unchanged":0}}