{"bal-disp":"61.41%","ballast":"3500 lbs. /  1588 kgs.","beam":"7.95' /  2.42m","builder":"Clark Boat Co. (USA)","builders":{"built-by":{"link":"view_builder.asp?builder_id=34","text":"Clark Boat Company"}},"construct":"FG","designer":"David Pedrick","designers":{"designed-by":{"link":"view_designer.asp?designer_id=125","text":"David Pedrick"}},"disp":"5700 lbs./  2586 kgs.","disp-len":"118.44","draft-max":"5.50' /  1.68m","first-built":"1981","hull-type":"Fin w/spade rudder","id":"854","imgs":[{"link":"imagehelper.asp?file_id=6149","text":"San Juan 33S drawing on sailboatdata.com"}],"last-built":"1982","listed-sa":"464 ft2 /  43.11 m2","loa":"33.10' /  10.09m","lwl":"27.80' /  8.47m","name":"SAN JUAN 33S","notes":"Thanks to Craig Montague for providing additional information on this yacht.","rig-dimensions":{"dl-ratio":"118.44","est-forestay-len":"36.93' /  11.26m","sa-disp":"23.34","safore":"201.47 ft2 /  18.72 m2","samain":"262.60 ft2 /  24.40 m2","spl":"12' /  3.66m","totalcalcsa":"464.07 ft2 /  43.11 m2"},"rig-type":"Fractional  Sloop","sa-disp":"23.34","update":{"deleted":0,"errors":0,"inserted":0,"replaced":1,"skipped":0,"unchanged":0}}