{"bal-disp":"36.59%","ballast":"3000 lbs. /  1361 kgs.","beam":"10.00' /  3.05m","builder":"Lancer Yacht Corp.","builders":{"built-by":{"link":"view_builder.asp?builder_id=98","text":"Lancer Yacht Corp. (USA)"}},"construct":"FG","designer":"C&C","designers":{"designed-by":{"link":"view_designer.asp?designer_id=113","text":"Cuthbertson & Cassian"}},"disp":"8200 lbs./  3720 kgs.","disp-len":"264.81","draft-max":"5.20' /  1.58m","first-built":"1979","hull-type":"Fin (shoal draft)","id":"873","imgs":[],"listed-sa":"368 ft2 /  34.19 m2","loa":"29.50' /  8.99m","lwl":"24.00' /  7.32m","name":"LANCER 30-3","rig-dimensions":{"dl-ratio":"264.81","e":"9.80' /  2.99m","est-forestay-len":"37.30' /  11.37m","i":"35.00' /  10.67m","j":"12.90' /  3.93m","p":"29.00' /  8.84m","sa-disp":"14.52","safore":"225.75 ft2 /  20.97 m2","samain":"142.10 ft2 /  13.20 m2","totalcalcsa":"367.85 ft2 /  34.17 m2"},"rig-type":"Masthead Sloop","sa-disp":"14.53","update":{"deleted":0,"errors":0,"inserted":0,"replaced":1,"skipped":0,"unchanged":0}}