{"aux-power":{"hp":"9","make":"Yanmar","type":"Diesel"},"bal-disp":"43.75%","ballast":"3086 lbs. /  1400 kgs.","beam":"10.00' /  3.05m","builder":"Dehler (GER)","builders":{"built-by":{"link":"view_builder.asp?builder_id=55","text":"Dehler Yachts"}},"construct":"FG","designer":"E. G. van de Stadt","designers":{"designed-by":{"link":"view_designer.asp?designer_id=35","text":"E. G. van de Stadt"}},"disp":"7055 lbs./  3200 kgs.","disp-len":"220.31","draft-max":"4.75' /  1.45m","first-built":"1984","hull-type":"Fin w/spade rudder","id":"881","imgs":[{"link":"imagehelper.asp?file_id=8861","text":"Dehler 31 drawing on sailboatdata.com"}],"listed-sa":"444 ft2 /  41.25 m2","loa":"30.84' /  9.40m","lwl":"24.27' /  7.40m","name":"DEHLER 31","notes":"VDS #392. Also called DEHLER 32.","rig-dimensions":{"dl-ratio":"220.31","e":"13.50' /  4.11m","est-forestay-len":"36.84' /  11.23m","i":"35.10' /  10.70m","j":"11.20' /  3.41m","p":"36.70' /  11.19m","sa-disp":"19.39","safore":"196.56 ft2 /  18.26 m2","samain":"247.73 ft2 /  23.01 m2","totalcalcsa":"444.29 ft2 /  41.27 m2"},"rig-type":"Fractional  Sloop","sa-disp":"19.37","update":{"deleted":0,"errors":0,"inserted":0,"replaced":1,"skipped":0,"unchanged":0}}